LICENSE
README.md
pyproject.toml
setup.cfg
setup.py
sqlalchemy_cubrid/__init__.py
sqlalchemy_cubrid/base.py
sqlalchemy_cubrid/compiler.py
sqlalchemy_cubrid/dialect.py
sqlalchemy_cubrid/types.py
sqlalchemy_cubrid.egg-info/PKG-INFO
sqlalchemy_cubrid.egg-info/SOURCES.txt
sqlalchemy_cubrid.egg-info/dependency_links.txt
sqlalchemy_cubrid.egg-info/entry_points.txt
sqlalchemy_cubrid.egg-info/requires.txt
sqlalchemy_cubrid.egg-info/top_level.txt