Metadata-Version: 2.1
Name: sqlalchemy-cubrid
Version: 0.0.1.dev1
Summary: Cubrid dialect for SQLAlchemy
Author: Yeongseon Choe, Gyeongjun Paik
Author-email: yeongseon.choe@gmail.com, paikend@gmail.com
License: MIT
Keywords: SQLAlchemy Cubrid
Classifier: Development Status :: 3 - Alpha
Classifier: Environment :: Console
Classifier: Intended Audience :: Developers
Classifier: License :: OSI Approved :: MIT License
Classifier: Programming Language :: Python
Classifier: Programming Language :: Python :: 3.7
License-File: LICENSE
